pyspark_msgraph_source/__init__.py
pyspark_msgraph_source/core/__init__.py
pyspark_msgraph_source/core/async_iterator.py
pyspark_msgraph_source/core/base_client.py
pyspark_msgraph_source/core/constants.py
pyspark_msgraph_source/core/models.py
pyspark_msgraph_source/core/resource_provider.py
pyspark_msgraph_source/core/source.py
pyspark_msgraph_source/core/utils.py
pyspark_msgraph_source/resources/__init__.py
pyspark_msgraph_source/resources/list_items.py
pyspark_msgraph_source-0.3.0.dist-info/LICENSE
pyspark_msgraph_source-0.3.0.dist-info/METADATA
pyspark_msgraph_source-0.3.0.dist-info/WHEEL
pyspark_msgraph_source-0.3.0.dist-info/RECORD
