Metadata-Version: 2.3
Name: pyspark_msgraph_source
Version: 0.3.0
Summary: Pyspark custom data source for Microsoft Graph APIs, including path and query parameters, with PySpark read examples.
Author: geekwhocodes
Author-email: ganeshraskar@outlook.com
Requires-Python: >=3.10,<4
Classifier: Programming Language :: Python :: 3
Classifier: Programming Language :: Python :: 3.10
Classifier: Programming Language :: Python :: 3.11
Classifier: Programming Language :: Python :: 3.12
Classifier: Programming Language :: Python :: 3.13
Requires-Dist: azure-identity
Requires-Dist: microsoft-kiota-serialization-json
Requires-Dist: msgraph-sdk
